lateco/__init__.py
lateco/Items.py
lateco/Searchengine.py
lateco/SentiWs.py
lateco/Tagsets.py
lateco-0.4.1.dist-info/METADATA
lateco-0.4.1.dist-info/WHEEL
lateco-0.4.1.dist-info/RECORD
