Metadata-Version: 2.1
Name: lateco
Version: 0.4.1
Summary: A framework for creating, managing and analysing large text corpora
License: Apache-2.0
Author: Thomas Zastrow
Author-email: post@thomas-zastrow.de
Requires-Python: ==3.*
Classifier: License :: OSI Approved :: Apache Software License
Classifier: Programming Language :: Python :: 3
Classifier: Programming Language :: Python :: 3.4
Classifier: Programming Language :: Python :: 3.5
Classifier: Programming Language :: Python :: 3.6
Classifier: Programming Language :: Python :: 3.7
Classifier: Programming Language :: Python :: 3.8
Classifier: Programming Language :: Python :: 3.9
Classifier: Programming Language :: Python :: 3.10
Classifier: Programming Language :: Python :: 3.11
Classifier: Programming Language :: Python :: 3.12
Classifier: Programming Language :: Python :: 3.13
Requires-Dist: elasticsearch
Requires-Dist: pandas
